qutech_util/__init__.py
qutil/__init__.py
qutil/__init__.pyi
qutil/caching.py
qutil/const.py
qutil/domains.py
qutil/functools.py
qutil/image.py
qutil/io.py
qutil/itertools.py
qutil/linalg.py
qutil/math.py
qutil/matlab.py
qutil/misc.py
qutil/pandas_tools.py
qutil/parallel.py
qutil/qcodes.py
qutil/qi.py
qutil/random.py
qutil/typecheck.py
qutil/electronics/__init__.py
qutil/electronics/__init__.pyi
qutil/electronics/lumped_elements.py
qutil/hardware/__init__.py
qutil/hardware/smart_test.py
qutil/measurement/__init__.py
qutil/measurement/__init__.pyi
qutil/measurement/spectrometer/__init__.py
qutil/plotting/__init__.py
qutil/plotting/__init__.pyi
qutil/plotting/colors.py
qutil/plotting/core.py
qutil/plotting/live_view.py
qutil/plotting/notex.mplstyle
qutil/plotting/presentation_notex.mplstyle
qutil/plotting/presentation_tex.mplstyle
qutil/plotting/publication_aps_notex.mplstyle
qutil/plotting/publication_aps_tex.mplstyle
qutil/plotting/rwth_colors.mplstyle
qutil/plotting/rwth_colors10.mplstyle
qutil/plotting/rwth_colors100.mplstyle
qutil/plotting/rwth_colors25.mplstyle
qutil/plotting/rwth_colors50.mplstyle
qutil/plotting/rwth_colors75.mplstyle
qutil/plotting/tex.mplstyle
qutil/plotting/thesis_tex.mplstyle
qutil/signal_processing/__init__.py
qutil/signal_processing/__init__.pyi
qutil/signal_processing/_common.py
qutil/signal_processing/fourier_space.py
qutil/signal_processing/real_space.py
qutil/ui/__init__.py
qutil/ui/__init__.pyi
qutil/ui/core.py
qutil/ui/gate_layout/__init__.py
qutil/ui/gate_layout/__init__.pyi
qutil/ui/gate_layout/core.py
qutil/ui/gate_layout/qcodes.py
qutech_util-2025.8.1.dist-info/METADATA
qutech_util-2025.8.1.dist-info/WHEEL
qutech_util-2025.8.1.dist-info/licenses/LICENSE
qutech_util-2025.8.1.dist-info/RECORD
