Metadata-Version: 2.4
Name: qutech-util
Version: 2025.8.1
Summary: Utility package of the Quantum Technology group of RWTH Aachen
Project-URL: Homepage, https://git.rwth-aachen.de/qutech/qutil
Author: Quantum Technology Group, RWTH Aachen University
License-Expression: GPL-3.0
License-File: LICENSE
Classifier: Intended Audience :: Science/Research
Classifier: License :: OSI Approved :: GNU General Public License v3 (GPLv3)
Classifier: Programming Language :: Python :: 3
Classifier: Programming Language :: Python :: 3.9
Classifier: Programming Language :: Python :: 3.10
Classifier: Programming Language :: Python :: 3.11
Classifier: Programming Language :: Python :: 3.12
Classifier: Programming Language :: Python :: 3.13
Classifier: Topic :: Scientific/Engineering :: Physics
Classifier: Topic :: Utilities
Requires-Python: >=3.9
Requires-Dist: dill
Requires-Dist: lazy-loader
Requires-Dist: matplotlib>=3.7
Requires-Dist: more-itertools
Requires-Dist: numpy
Requires-Dist: packaging
Requires-Dist: pandas
Requires-Dist: scipy
Requires-Dist: typeguard
Provides-Extra: all
Requires-Dist: colorspacious; extra == 'all'
Requires-Dist: ezdxf; extra == 'all'
Requires-Dist: fastz; extra == 'all'
Requires-Dist: hdf5storage; extra == 'all'
Requires-Dist: moviepy; extra == 'all'
Requires-Dist: myst-parser; extra == 'all'
Requires-Dist: pydata-sphinx-theme; extra == 'all'
Requires-Dist: pyserial; extra == 'all'
Requires-Dist: qcodes; extra == 'all'
Requires-Dist: qcodes-loop; extra == 'all'
Requires-Dist: sphinx; extra == 'all'
Requires-Dist: tifffile[all]; extra == 'all'
Requires-Dist: tqdm; extra == 'all'
Requires-Dist: xarray; extra == 'all'
Provides-Extra: colormaps
Requires-Dist: colorspacious; extra == 'colormaps'
Provides-Extra: complete
Requires-Dist: colorspacious; extra == 'complete'
Requires-Dist: ezdxf; extra == 'complete'
Requires-Dist: fastz; extra == 'complete'
Requires-Dist: hdf5storage; extra == 'complete'
Requires-Dist: moviepy; extra == 'complete'
Requires-Dist: myst-parser; extra == 'complete'
Requires-Dist: pydata-sphinx-theme; extra == 'complete'
Requires-Dist: pyserial; extra == 'complete'
Requires-Dist: qcodes; extra == 'complete'
Requires-Dist: qcodes-loop; extra == 'complete'
Requires-Dist: sphinx; extra == 'complete'
Requires-Dist: tifffile[all]; extra == 'complete'
Requires-Dist: tqdm; extra == 'complete'
Requires-Dist: xarray; extra == 'complete'
Provides-Extra: doc
Requires-Dist: myst-parser; extra == 'doc'
Requires-Dist: pydata-sphinx-theme; extra == 'doc'
Requires-Dist: sphinx; extra == 'doc'
Provides-Extra: electronics
Requires-Dist: fastz; extra == 'electronics'
Provides-Extra: fancy-progressbar
Requires-Dist: tqdm; extra == 'fancy-progressbar'
Provides-Extra: gl
Requires-Dist: ezdxf; extra == 'gl'
Provides-Extra: hardware
Requires-Dist: pyserial; extra == 'hardware'
Provides-Extra: image
Requires-Dist: moviepy; extra == 'image'
Requires-Dist: tifffile[all]; extra == 'image'
Provides-Extra: matlab
Requires-Dist: hdf5storage; extra == 'matlab'
Requires-Dist: xarray; extra == 'matlab'
Provides-Extra: qcodes
Requires-Dist: qcodes; extra == 'qcodes'
Requires-Dist: qcodes-loop; extra == 'qcodes'
